enterprise_outliers/__init__.py
enterprise_outliers/base.py
enterprise_outliers/choleskyext_omp.cpython-310-darwin.so
enterprise_outliers/funnel.py
enterprise_outliers/gibbs_outlier.py
enterprise_outliers/hmc_outlier.py
enterprise_outliers/interval.py
enterprise_outliers/jitterext.cpython-310-darwin.so
enterprise_outliers/nutstrajectory.py
enterprise_outliers/pulsar.py
enterprise_outliers/utils.py
enterprise_outliers-1.0.0.dist-info/AUTHORS.rst
enterprise_outliers-1.0.0.dist-info/LICENSE
enterprise_outliers-1.0.0.dist-info/METADATA
enterprise_outliers-1.0.0.dist-info/WHEEL
enterprise_outliers-1.0.0.dist-info/top_level.txt
enterprise_outliers-1.0.0.dist-info/RECORD
