Metadata-Version: 2.1
Name: enterprise-outliers
Version: 1.0.0
Summary: Outlier analysis
Home-page: https://github.com/nanograv/enterprise_outliers
Author: Stephen R. Taylor, Paul T. Baker, Jeffrey S. Hazboun, Sarah Vigeland
Author-email: srtaylor@caltech.edu
License: MIT
Keywords: gravitational-wave,black-hole binary,pulsar-timing arrays
Classifier: Topic :: Scientific/Engineering :: Astronomy
Classifier: Topic :: Scientific/Engineering :: Physics
Classifier: Topic :: Scientific/Engineering :: Mathematics
Classifier: Intended Audience :: Science/Research
Classifier: Programming Language :: Python :: 3
Classifier: Topic :: Software Development :: Libraries :: Python Modules
License-File: LICENSE
License-File: AUTHORS.rst
Requires-Dist: numpy (>=1.16.3)
Requires-Dist: scipy (>=1.2.0)
Requires-Dist: Cython (>=0.28.5)
Requires-Dist: scikit-sparse (>=0.4.5)
Requires-Dist: enterprise-pulsar (>=3.1.0)
Requires-Dist: pint-pulsar (>=0.8.3)
Requires-Dist: matplotlib (>=3.2.0)
Requires-Dist: numdifftools (>=0.9.0)
